{"atividade_principal":[{"text":"Transmissão de energia elétrica","code":"35.12-3-00"}],"data_situacao":"03/11/2005","nome":"ELETROSUL CENTRAIS ELETRICAS S/A","efr":"UNIÃO","uf":"SC","atividades_secundarias":[{"text":"Geração de energia elétrica","code":"35.11-5-01"}],"qsa":[{"qual":"16-Presidente","nome":"GILBERTO ODILON EGGERS"},{"qual":"10-Diretor","nome":"TOME AUMARY GREGORIO"},{"qual":"10-Diretor","nome":"ROGERIO BONINI RUIZ"},{"qual":"10-Diretor","nome":"JAIME DE SOUZA"},{"qual":"10-Diretor","nome":"MARCOS ROMEU BENEDETTI"}],"situacao":"ATIVA","bairro":"PANTANAL","logradouro":"R DEP ANTONIO EDU VIEIRA","numero":"999","cep":"88.040-901","municipio":"FLORIANOPOLIS","porte":"DEMAIS","abertura":"31/07/1973","natureza_juridica":"203-8 - Sociedade de Economia Mista","fantasia":"ELETROSUL","cnpj":"00.073.957/0001-68","ultima_atualizacao":"2019-02-14T14:15:43.094Z","status":"OK","tipo":"MATRIZ","complemento":"","email":"","telefone":"","motivo_situacao":"","situacao_especial":"","data_situacao_especial":"","capital_social":"0.00","extra":{},"billing":{"free":true,"database":true}}