{"atividade_principal":[{"text":"Atividades de associações de defesa de direitos sociais","code":"94.30-8-00"}],"data_situacao":"24/12/2004","nome":"ASSOCIACAO POLICIAL MILITAR DE ASSISTENCIA A SAUDE","uf":"SP","telefone":"(17) 5211-294","email":"apomas@zup.com.br","atividades_secundarias":[{"text":"Atividades de organizações associativas ligadas à cultura e à arte","code":"94.93-6-00"},{"text":"Atividades associativas não especificadas anteriormente","code":"94.99-5-00"}],"qsa":[{"qual":"16-Presidente","nome":"LUIS CESAR CESTE"}],"situacao":"ATIVA","bairro":"VILA RODRIGUES","logradouro":"PC FELICIO TONELLO","numero":"164","cep":"15.801-321","municipio":"CATANDUVA","porte":"DEMAIS","abertura":"06/02/1995","natureza_juridica":"399-9 - Associação Privada","fantasia":"APOMAS","cnpj":"00.490.723/0001-16","ultima_atualizacao":"2019-03-06T18:58:10.147Z","status":"OK","tipo":"MATRIZ","complemento":"","efr":"","motivo_situacao":"","situacao_especial":"","data_situacao_especial":"","capital_social":"0.00","extra":{},"billing":{"free":true,"database":true}}