{"atividade_principal":[{"text":"Planos de saúde","code":"65.50-2-00"}],"data_situacao":"03/11/2005","nome":"CENTRO CLINICO GAUCHO LTDA","uf":"RS","telefone":"(51) 3287-9221","atividades_secundarias":[{"text":"Serviços combinados de escritório e apoio administrativo","code":"82.11-3-00"},{"text":"Atividade médica ambulatorial com recursos para realização de exames complementares","code":"86.30-5-02"},{"text":"Atividade odontológica","code":"86.30-5-04"},{"text":"Atividades de fisioterapia","code":"86.50-0-04"},{"text":"Atividade médica ambulatorial com recursos para realização de procedimentos cirúrgicos","code":"86.30-5-01"},{"text":"Serviços de diagnóstico por imagem com uso de radiação ionizante, exceto tomografia","code":"86.40-2-05"},{"text":"Serviços de diagnóstico por imagem sem uso de radiação ionizante, exceto ressonância magnética","code":"86.40-2-07"},{"text":"Serviços de diagnóstico por registro gráfico - ECG, EEG e outros exames análogos","code":"86.40-2-08"},{"text":"Atividades de psicologia e psicanálise","code":"86.50-0-03"},{"text":"Atividades de profissionais da nutrição","code":"86.50-0-02"},{"text":"Atividades de fonoaudiologia","code":"86.50-0-06"},{"text":"Atividade médica ambulatorial restrita a consultas","code":"86.30-5-03"},{"text":"Atividades de atenção ambulatorial não especificadas anteriormente","code":"86.30-5-99"},{"text":"Outras atividades de serviços prestados principalmente às empresas não especificadas anteriormente","code":"82.99-7-99"},{"text":"Comércio atacadista de medicamentos e drogas de uso humano","code":"46.44-3-01"}],"qsa":[{"qual":"49-Sócio-Administrador","nome":"LUIZ CLAUDIO LEOPOLDO"},{"qual":"49-Sócio-Administrador","nome":"FERNANDO VICO DA CUNHA"},{"qual":"49-Sócio-Administrador","nome":"CESAR FRANCO DE LIMA"},{"qual":"49-Sócio-Administrador","nome":"FRANCISCO ANTONIO SANTA HELENA"}],"situacao":"ATIVA","bairro":"NAVEGANTES","logradouro":"R DONA MARGARIDA","numero":"537","cep":"90.240-611","municipio":"PORTO ALEGRE","porte":"DEMAIS","abertura":"23/08/1995","natureza_juridica":"206-2 - Sociedade Empresária Limitada","cnpj":"00.773.639/0001-00","ultima_atualizacao":"2019-03-12T14:26:24.651Z","status":"OK","tipo":"MATRIZ","fantasia":"","complemento":"","email":"","efr":"","motivo_situacao":"","situacao_especial":"","data_situacao_especial":"","capital_social":"40713000.00","extra":{},"billing":{"free":true,"database":true}}