{"atividade_principal":[{"text":"Atividades de atendimento hospitalar, exceto pronto-socorro e unidades para atendimento a urgências","code":"86.10-1-01"}],"data_situacao":"04/10/2003","nome":"MEDICAL MEDICINA COOPERATIVA ASSISTENCIAL DE LIMEIRA","uf":"SP","qsa":[{"qual":"16-Presidente","nome":"JOAO CARLOS RODRIGUES DE ALMEIDA"}],"situacao":"ATIVA","bairro":"VL PARAISO","logradouro":"AV ANA C DE BARROS LEVY","numero":"124","cep":"13.480-755","municipio":"LIMEIRA","porte":"DEMAIS","abertura":"14/08/1996","natureza_juridica":"214-3 - Cooperativa","fantasia":"MEDICAL","cnpj":"01.370.425/0001-55","ultima_atualizacao":"2019-03-09T08:44:47.817Z","status":"OK","tipo":"MATRIZ","complemento":"","email":"","telefone":"","efr":"","motivo_situacao":"","situacao_especial":"","data_situacao_especial":"","atividades_secundarias":[{"code":"00.00-0-00","text":"Não informada"}],"capital_social":"0.00","extra":{},"billing":{"free":true,"database":true}}