{"atividade_principal":[{"text":"Planos de saúde","code":"65.50-2-00"}],"data_situacao":"03/06/1998","complemento":"SALA: 402; EDIF: AMERICA C EMPRESARIA;","nome":"CAIXA DE ASSISTENCIA A SAUDE DA UNIVERSIDADE","uf":"ES","telefone":"(27) 3315-0010","email":"contabilidade@casufes.org.br","qsa":[{"qual":"16-Presidente","nome":"ALEXANDRE RAMOS RICARDO"}],"situacao":"ATIVA","bairro":"MATA DA PRAIA","logradouro":"AV FERNANDO FERRARI","numero":"1080","cep":"29.066-380","municipio":"VITORIA","porte":"DEMAIS","abertura":"10/03/1998","natureza_juridica":"399-9 - Associação Privada","fantasia":"CASUFES","cnpj":"02.402.002/0001-32","ultima_atualizacao":"2019-02-14T13:14:44.170Z","status":"OK","tipo":"MATRIZ","efr":"","motivo_situacao":"","situacao_especial":"","data_situacao_especial":"","atividades_secundarias":[{"code":"00.00-0-00","text":"Não informada"}],"capital_social":"0.00","extra":{},"billing":{"free":true,"database":true}}