{"atividade_principal":[{"text":"Planos de saúde","code":"65.50-2-00"}],"data_situacao":"20/07/2002","complemento":"3 ANDAR","nome":"SEPACO SAUDE LTDA","uf":"SP","telefone":"(011) 5087-9000","email":"sepaco@sepaco.com.br","qsa":[{"qual":"49-Sócio-Administrador","nome":"RAFAEL ANTONIO PARRI"}],"situacao":"ATIVA","bairro":"VILA MARIANA","logradouro":"R VERGUEIRO","numero":"4210","cep":"04.102-002","municipio":"SAO PAULO","porte":"DEMAIS","abertura":"02/06/1999","natureza_juridica":"206-2 - Sociedade Empresária Limitada","fantasia":"SEPACO SAUDE","cnpj":"03.219.363/0001-00","ultima_atualizacao":"2019-02-22T21:25:27.450Z","status":"OK","tipo":"MATRIZ","efr":"","motivo_situacao":"","situacao_especial":"","data_situacao_especial":"","atividades_secundarias":[{"code":"00.00-0-00","text":"Não informada"}],"capital_social":"93000.00","extra":{},"billing":{"free":true,"database":true}}