{"atividade_principal":[{"text":"Planos de saúde","code":"65.50-2-00"}],"data_situacao":"03/11/2005","complemento":"ANDAR 2 CONJ 22","nome":"BIOVIDA SAUDE LTDA.","uf":"SP","telefone":"(11) 4063-8851","email":"controladoria@biovidasaude.com.br","qsa":[{"qual":"49-Sócio-Administrador","nome":"CARLOS ALBERTO DE ALMEIDA CAMPOS"},{"qual":"22-Sócio","nome":"RODRIGO TSUYOSHI DE ALMEIDA CAMPOS"}],"situacao":"ATIVA","bairro":"REPUBLICA","logradouro":"R BARAO DE ITAPETININGA","numero":"151","cep":"01.042-001","municipio":"SAO PAULO","porte":"DEMAIS","abertura":"09/02/2001","natureza_juridica":"206-2 - Sociedade Empresária Limitada","fantasia":"BIOVIDA SAUDE","cnpj":"04.299.138/0001-94","ultima_atualizacao":"2019-02-04T16:00:24.174Z","status":"OK","tipo":"MATRIZ","efr":"","motivo_situacao":"","situacao_especial":"","data_situacao_especial":"","atividades_secundarias":[{"code":"00.00-0-00","text":"Não informada"}],"capital_social":"9761200.00","extra":{},"billing":{"free":true,"database":true}}