{"atividade_principal":[{"text":"Sociedade seguradora de seguros saúde","code":"65.20-1-00"}],"data_situacao":"04/10/2003","complemento":"ANDAR 7 -PARTE","nome":"ALLIANZ SAUDE S.A.","uf":"SP","telefone":"(11) 3171-6883 / (11) 3171-6650","email":"josiane.pereira@allianz.com.br","qsa":[{"qual":"10-Diretor","nome":"REGINA HELENA MENEZES LOPES"},{"qual":"16-Presidente","nome":"EDUARD FOLCH RUE"},{"qual":"10-Diretor","nome":"MATTHIAS KUHN"}],"situacao":"ATIVA","bairro":"PINHEIROS","logradouro":"R EUGENIO DE MEDEIROS","numero":"303","cep":"05.425-000","municipio":"SAO PAULO","porte":"DEMAIS","abertura":"09/05/2001","natureza_juridica":"205-4 - Sociedade Anônima Fechada","cnpj":"04.439.627/0001-02","ultima_atualizacao":"2019-01-29T08:00:37.825Z","status":"OK","tipo":"MATRIZ","fantasia":"","efr":"","motivo_situacao":"","situacao_especial":"","data_situacao_especial":"","atividades_secundarias":[{"code":"00.00-0-00","text":"Não informada"}],"capital_social":"308580319.00","extra":{},"billing":{"free":true,"database":true}}