{"atividade_principal":[{"text":"Planos de saúde","code":"65.50-2-00"}],"data_situacao":"03/11/2005","nome":"UNIMED MACAPA COOPERATIVA DE TRABALHO MEDICO LTDA","uf":"AP","telefone":"(96) 3312-6055","atividades_secundarias":[{"text":"Atividades de atendimento hospitalar, exceto pronto-socorro e unidades para atendimento a urgências","code":"86.10-1-01"},{"text":"Atividades de atendimento em pronto-socorro e unidades hospitalares para atendimento a urgências","code":"86.10-1-02"},{"text":"Serviços de remoção de pacientes, exceto os serviços móveis de atendimento a urgências","code":"86.22-4-00"},{"text":"Atividade médica ambulatorial com recursos para realização de exames complementares","code":"86.30-5-02"},{"text":"Laboratórios clínicos","code":"86.40-2-02"},{"text":"Serviços de diagnóstico por imagem com uso de radiação ionizante, exceto tomografia","code":"86.40-2-05"},{"text":"Serviços de diagnóstico por imagem sem uso de radiação ionizante, exceto ressonância magnética","code":"86.40-2-07"},{"text":"Serviços de diagnóstico por registro gráfico - ECG, EEG e outros exames análogos","code":"86.40-2-08"},{"text":"Serviços de diagnóstico por métodos ópticos - endoscopia e outros exames análogos","code":"86.40-2-09"},{"text":"Atividades de profissionais da nutrição","code":"86.50-0-02"},{"text":"Atividades de psicologia e psicanálise","code":"86.50-0-03"},{"text":"Atividades de fisioterapia","code":"86.50-0-04"},{"text":"Atividades de apoio à gestão de saúde","code":"86.60-7-00"},{"text":"Outras atividades de atenção à saúde humana não especificadas anteriormente","code":"86.90-9-99"}],"qsa":[{"qual":"10-Diretor","nome":"GLADSTONE JOSE COELHO GONCALVES"},{"qual":"10-Diretor","nome":"CARLOS MARCO SANTOS GALAN"},{"qual":"10-Diretor","nome":"MAURO CAMILO MENDES QUEIROZ"},{"qual":"10-Diretor","nome":"MARIA DAS GRACAS CREAO SALGADO"},{"qual":"10-Diretor","nome":"SELMA MARIA DAGHER"},{"qual":"10-Diretor","nome":"JOSE MARIA OLIVEIRA DE AZEVEDO"},{"qual":"10-Diretor","nome":"ROSILENE LOPES TRINDADE"},{"qual":"10-Diretor","nome":"EDWARD EYI FOSTER"},{"qual":"10-Diretor","nome":"SANDRA REGINA DOS ANJOS MIRANDA"},{"qual":"16-Presidente","nome":"ROSALIA MARIA GOMES DE FREITAS"},{"qual":"10-Diretor","nome":"ELZA MARIA REZENDE DE ALMEIDA"},{"qual":"10-Diretor","nome":"ROZENI FERREIRA SONNY"}],"situacao":"ATIVA","bairro":"MARCO ZERO","logradouro":"R SAMUEL TRAJANO DE SOUZA,","numero":"429","cep":"68.903-901","municipio":"MACAPA","porte":"DEMAIS","abertura":"20/02/1986","natureza_juridica":"214-3 - Cooperativa","fantasia":"UNIMED MACAPA COOP.DE TRAB MEDICO - SEDE ADM","cnpj":"10.225.225/0001-08","ultima_atualizacao":"2019-03-14T12:08:51.814Z","status":"OK","tipo":"MATRIZ","complemento":"","email":"","efr":"","motivo_situacao":"","situacao_especial":"","data_situacao_especial":"","capital_social":"0.00","extra":{},"billing":{"free":true,"database":true}}