{"atividade_principal":[{"text":"Planos de saúde","code":"65.50-2-00"}],"data_situacao":"03/11/2005","complemento":"EDIF: CENTRO MEDICO; : EMPRESARIAL VITRAUX; : SALAS 101 A 104; : 201 A 204; : 303; : 1401 A 1404;","nome":"PROMEDICA - PROTECAO MEDICA A EMPRESAS S.A.","uf":"BA","telefone":"(71) 3271-9165 / (71) 3271-9169","email":"promedica@promedica.com.br","atividades_secundarias":[{"text":"Outras sociedades de participação, exceto holdings","code":"64.63-8-00"},{"text":"Atividades de atendimento hospitalar, exceto pronto-socorro e unidades para atendimento a urgências","code":"86.10-1-01"},{"text":"Atividade médica ambulatorial com recursos para realização de procedimentos cirúrgicos","code":"86.30-5-01"},{"text":"Atividade médica ambulatorial com recursos para realização de exames complementares","code":"86.30-5-02"},{"text":"Atividade médica ambulatorial restrita a consultas","code":"86.30-5-03"},{"text":"Serviços de vacinação e imunização humana","code":"86.30-5-06"},{"text":"Atividades de atenção ambulatorial não especificadas anteriormente","code":"86.30-5-99"},{"text":"Laboratórios de anatomia patológica e citológica","code":"86.40-2-01"},{"text":"Laboratórios clínicos","code":"86.40-2-02"},{"text":"Serviços de diagnóstico por imagem com uso de radiação ionizante, exceto tomografia","code":"86.40-2-05"},{"text":"Serviços de diagnóstico por imagem sem uso de radiação ionizante, exceto ressonância magnética","code":"86.40-2-07"},{"text":"Serviços de diagnóstico por métodos ópticos - endoscopia e outros exames análogos","code":"86.40-2-09"},{"text":"Atividades de profissionais da nutrição","code":"86.50-0-02"},{"text":"Atividades de psicologia e psicanálise","code":"86.50-0-03"},{"text":"Atividades de fisioterapia","code":"86.50-0-04"},{"text":"Atividades de fornecimento de infra-estrutura de apoio e assistência a paciente no domicílio","code":"87.12-3-00"}],"qsa":[{"qual":"16-Presidente","nome":"TEREZA RITA LEONY VALENTE"},{"qual":"10-Diretor","nome":"ERALDO DIAS MOURA COSTA"},{"qual":"10-Diretor","nome":"JORGE ANTONIO DUARTE OLIVEIRA"}],"situacao":"ATIVA","bairro":"RIO VERMELHO","logradouro":"R SOL NASCENTE","numero":"43","cep":"41.940-457","municipio":"SALVADOR","porte":"DEMAIS","abertura":"27/03/1969","natureza_juridica":"205-4 - Sociedade Anônima Fechada","fantasia":"PROMEDICA","cnpj":"15.214.919/0001-55","ultima_atualizacao":"2019-03-08T18:55:43.553Z","status":"OK","tipo":"MATRIZ","efr":"","motivo_situacao":"","situacao_especial":"","data_situacao_especial":"","capital_social":"33172734.00","extra":{},"billing":{"free":true,"database":true}}