{"atividade_principal":[{"text":"Previdência complementar fechada","code":"65.41-3-00"}],"data_situacao":"03/11/2005","complemento":"CAMPUS UNIVERSITARIO","nome":"AGROS INSTITUTO UFV DE SEGURIDADE SOCIAL","uf":"MG","telefone":"(31) 3899-3500","email":"dge@agros.org.br","atividades_secundarias":[{"text":"Planos de saúde","code":"65.50-2-00"}],"qsa":[{"qual":"10-Diretor","nome":"NAIRAM FELIX DE BARROS"}],"situacao":"ATIVA","bairro":"CAMPUS UFV","logradouro":"AV PURDUE","numero":"S/N","cep":"36.570-001","municipio":"VICOSA","porte":"DEMAIS","abertura":"19/11/1979","natureza_juridica":"399-9 - Associação Privada","cnpj":"20.320.487/0001-05","ultima_atualizacao":"2019-03-26T21:00:50.468Z","status":"OK","tipo":"MATRIZ","fantasia":"","efr":"","motivo_situacao":"","situacao_especial":"","data_situacao_especial":"","capital_social":"0.00","extra":{},"billing":{"free":true,"database":true}}