{"atividade_principal":[{"text":"Planos de saúde","code":"65.50-2-00"}],"data_situacao":"03/11/2005","nome":"CLIMOL CLINICA M E ODONTOLOGICA S F DE ASSIS LTDA","uf":"RJ","atividades_secundarias":[{"text":"Atividade médica ambulatorial com recursos para realização de exames complementares","code":"86.30-5-02"},{"text":"Atividade médica ambulatorial com recursos para realização de procedimentos cirúrgicos","code":"86.30-5-01"},{"text":"Atividade médica ambulatorial restrita a consultas","code":"86.30-5-03"},{"text":"Atividade odontológica","code":"86.30-5-04"},{"text":"Atividades de atenção ambulatorial não especificadas anteriormente","code":"86.30-5-99"},{"text":"Serviços de vacinação e imunização humana","code":"86.30-5-06"}],"qsa":[{"qual":"49-Sócio-Administrador","nome":"MARIA DE FATIMA DOS SANTOS VIANA DRUMMOND"},{"qual":"49-Sócio-Administrador","nome":"MARIO MARTINS DE CAMPOS VIANA"}],"situacao":"ATIVA","bairro":"CENTRO","logradouro":"AV GETULIO DE MOURA","numero":"998","cep":"26.262-020","municipio":"NOVA IGUACU","porte":"DEMAIS","abertura":"15/06/1988","natureza_juridica":"206-2 - Sociedade Empresária Limitada","cnpj":"32.076.630/0001-36","ultima_atualizacao":"2019-01-07T13:46:20.893Z","status":"OK","tipo":"MATRIZ","fantasia":"","complemento":"","email":"","telefone":"","efr":"","motivo_situacao":"","situacao_especial":"","data_situacao_especial":"","capital_social":"290000.00","extra":{},"billing":{"free":true,"database":true}}