{"atividade_principal":[{"text":"Extração de minério de ferro","code":"07.10-3-01"}],"data_situacao":"03/11/2005","complemento":"SAL 701 801 901 1001 1101 1201 1301 1401 1501 1601 1701 1801 1901","nome":"VALE S.A.","uf":"RJ","telefone":"(21) 3485-3002","email":"danilo.cidrini@vale.com","atividades_secundarias":[{"text":"Atividades de apoio à extração de minério de ferro","code":"09.90-4-01"},{"text":"Serviços combinados de escritório e apoio administrativo","code":"82.11-3-00"}],"qsa":[{"qual":"10-Diretor","nome":"GERD PETER POPPINGA"},{"qual":"10-Diretor","nome":"LUCIANO SIANI PIRES"},{"qual":"16-Presidente","nome":"FABIO SCHVARTSMAN"},{"qual":"10-Diretor","nome":"LUIZ EDUARDO FROES DO AMARAL OSORIO"},{"qual":"10-Diretor","nome":"ALEXANDRE GOMES PEREIRA"},{"qual":"10-Diretor","nome":"EDUARDO DE SALLES BARTOLOMEO"}],"situacao":"ATIVA","bairro":"BOTAFOGO","logradouro":"PR BOTAFOGO","numero":"00186","cep":"22.250-145","municipio":"RIO DE JANEIRO","porte":"DEMAIS","abertura":"11/02/1969","natureza_juridica":"204-6 - Sociedade Anônima Aberta","cnpj":"33.592.510/0001-54","ultima_atualizacao":"2019-03-12T16:28:56.966Z","status":"OK","tipo":"MATRIZ","fantasia":"","efr":"","motivo_situacao":"","situacao_especial":"","data_situacao_especial":"","capital_social":"77300000000.00","extra":{},"billing":{"free":true,"database":true}}