{"atividade_principal":[{"text":"Previdência complementar fechada","code":"65.41-3-00"}],"data_situacao":"22/10/2005","complemento":"9 PARTE A 13 ANDAR","nome":"TELOS FUNDACAO EMBRATEL DE SEGURIDADE SOCIAL","uf":"RJ","telefone":"(0021) 2121-6701","qsa":[{"qual":"16-Presidente","nome":"ROBERTO DURAES DE PINHO"},{"qual":"10-Diretor","nome":"ANDREA MORANGO PITTIGLIANI"},{"qual":"10-Diretor","nome":"CARLOS ALBERTO TAVARES DE ALMEIDA"}],"situacao":"ATIVA","bairro":"CENTRO","logradouro":"AV PRESIDENTE VARGAS","numero":"290","cep":"20.071-000","municipio":"RIO DE JANEIRO","abertura":"23/07/1975","natureza_juridica":"399-9 - Associação Privada","fantasia":"ESTABELECIMENTO UNIFICADO","porte":"DEMAIS","cnpj":"42.465.310/0001-21","ultima_atualizacao":"2018-12-28T23:09:05.234Z","status":"OK","tipo":"MATRIZ","email":"","efr":"","motivo_situacao":"","situacao_especial":"","data_situacao_especial":"","atividades_secundarias":[{"code":"00.00-0-00","text":"Não informada"}],"capital_social":"0.00","extra":{},"billing":{"free":true,"database":true}}