{"atividade_principal":[{"text":"Planos de saúde","code":"65.50-2-00"}],"data_situacao":"04/10/2003","nome":"UNIMED DE CACAPAVA COOPERATIVA DE TRABALHO MEDICO","uf":"SP","telefone":"(12) 3654-8600 / (12) 3654-8623","email":"contabilidade@unimedcpv.com.br","qsa":[{"qual":"16-Presidente","nome":"PAULO DE SA LEITE MARTINS"},{"qual":"10-Diretor","nome":"LUIZ EDUARDO AZEVEDO FERRETTI"},{"qual":"10-Diretor","nome":"DANILO GARCIA DE ARAUJO"}],"situacao":"ATIVA","bairro":"CENTRO","logradouro":"R CORONEL JOAO DIAS GUIMARAES","numero":"435","cep":"12.281-350","municipio":"CACAPAVA","porte":"DEMAIS","abertura":"08/02/1982","natureza_juridica":"214-3 - Cooperativa","cnpj":"48.721.401/0001-67","ultima_atualizacao":"2019-03-09T04:21:40.598Z","status":"OK","tipo":"MATRIZ","fantasia":"","complemento":"","efr":"","motivo_situacao":"","situacao_especial":"","data_situacao_especial":"","atividades_secundarias":[{"code":"00.00-0-00","text":"Não informada"}],"capital_social":"0.00","extra":{},"billing":{"free":true,"database":true}}